[
    {
        "I1": -4.441,
        "I2": -12.68,
        "I3": 13.881,
        "I4": -0.169,
        "I5": -9.944,
        "I6": -4.85,
        "I7": 4.408,
        "I8": -15.399,
        "X1": -19.555,
        "Y1": -79.34,
        "Z1": 84.588,
        "X2": -11.567,
        "Y2": -40.641,
        "Z2": 0.427
    },
    {
        "I1": 13.357,
        "I2": 9.266,
        "I3": 1.551,
        "I4": -0.748,
        "I5": -9.344,
        "I6": -17.507,
        "I7": -0.829,
        "I8": -13.112,
        "X1": 4.761,
        "Y1": 62.839,
        "Z1": 20.421,
        "X2": -50.585,
        "Y2": 21.303,
        "Z2": 5.638
    },
    {
        "I1": -4.442,
        "I2": 6.491,
        "I3": 16.665,
        "I4": -6.5,
        "I5": -12.974,
        "I6": -16.974,
        "I7": 12.738,
        "I8": -15.085,
        "X1": -83.044,
        "Y1": 45.452,
        "Z1": 22.489,
        "X2": -97.206,
        "Y2": -52.907,
        "Z2": 93.971
    }
]